[
  {
    "ContainingType": "OrderAndCargo.API.Controllers.OrdersController",
    "Method": "CreateOrder",
    "RelativePath": "api/Orders",
    "HttpMethod": "POST",
    "IsController": true,
    "Order": 0,
    "Parameters": [
      {
        "Name": "command",
        "Type": "OrderAndCargo.Application.Commands.CreateOrderCommand",
        "IsRequired": true
      }
    ],
    "ReturnTypes": []
  },
  {
    "ContainingType": "OrderAndCargo.API.Controllers.OrdersController",
    "Method": "GetOrders",
    "RelativePath": "api/Orders",
    "HttpMethod": "GET",
    "IsController": true,
    "Order": 0,
    "Parameters": [],
    "ReturnTypes": []
  },
  {
    "ContainingType": "OrderAndCargo.API.Controllers.OrdersController",
    "Method": "Update",
    "RelativePath": "api/Orders/{id}",
    "HttpMethod": "PUT",
    "IsController": true,
    "Order": 0,
    "Parameters": [
      {
        "Name": "id",
        "Type": "System.Guid",
        "IsRequired": true
      },
      {
        "Name": "command",
        "Type": "OrderAndCargo.Application.Commands.UpdateOrderCommand",
        "IsRequired": true
      }
    ],
    "ReturnTypes": []
  },
  {
    "ContainingType": "OrderAndCargo.API.Controllers.OrdersController",
    "Method": "Delete",
    "RelativePath": "api/Orders/{id}",
    "HttpMethod": "DELETE",
    "IsController": true,
    "Order": 0,
    "Parameters": [
      {
        "Name": "id",
        "Type": "System.Guid",
        "IsRequired": true
      }
    ],
    "ReturnTypes": []
  },
  {
    "ContainingType": "OrderAndCargo.API.Controllers.ProductsController",
    "Method": "Update",
    "RelativePath": "api/Products/{id}",
    "HttpMethod": "PUT",
    "IsController": true,
    "Order": 0,
    "Parameters": [
      {
        "Name": "id",
        "Type": "System.Guid",
        "IsRequired": true
      },
      {
        "Name": "updatedProduct",
        "Type": "OrderAndCargo.Domain.Entities.Product",
        "IsRequired": true
      }
    ],
    "ReturnTypes": []
  },
  {
    "ContainingType": "OrderAndCargo.API.Controllers.ProductsController",
    "Method": "Delete",
    "RelativePath": "api/Products/{id}",
    "HttpMethod": "DELETE",
    "IsController": true,
    "Order": 0,
    "Parameters": [
      {
        "Name": "id",
        "Type": "System.Guid",
        "IsRequired": true
      }
    ],
    "ReturnTypes": []
  },
  {
    "ContainingType": "OrderAndCargo.API.Controllers.WeatherForecastController",
    "Method": "Get",
    "RelativePath": "WeatherForecast",
    "HttpMethod": "GET",
    "IsController": true,
    "Order": 0,
    "Parameters": [],
    "ReturnTypes": [
      {
        "Type": "System.Collections.Generic.IEnumerable\u00601[[OrderAndCargo.API.WeatherForecast, OrderAndCargo.API, Version=1.0.0.0, Culture=neutral, PublicKeyToken=null]]",
        "MediaTypes": [
          "text/plain",
          "application/json",
          "text/json"
        ],
        "StatusCode": 200
      }
    ],
    "EndpointName": "GetWeatherForecast"
  }
]